_tpcb/tpcb.py
tpcb-0.1.dist-info/METADATA
tpcb-0.1.dist-info/WHEEL
tpcb-0.1.dist-info/entry_points.txt
tpcb-0.1.dist-info/top_level.txt
tpcb-0.1.dist-info/zip-safe
tpcb-0.1.dist-info/RECORD
