Metadata-Version: 2.1
Name: tpcb
Version: 0.1
Summary: A command-line utility that converts the text in clipboard intokeystrokes after a given amount of time (default: 2sec).
Home-page: https://github.com/5j9/tpcb
Author: 5j9
Author-email: 5j9@users.noreply.github.com
License: GNU General Public License v3 (GPLv3)
Keywords: convert type clipboard paste keystroke
Platform: UNKNOWN
Classifier: Environment :: Console
Classifier: Natural Language :: English
Classifier: Intended Audience :: End Users/Desktop
Classifier: License :: OSI Approved :: GNU General Public License v3 or later (GPLv3+)
Classifier: Programming Language :: Python :: 3 :: Only
Classifier: Programming Language :: Python :: 3
Classifier: Programming Language :: Python :: 3.6
Classifier: Programming Language :: Python :: 3.7
Classifier: Programming Language :: Python :: 3.8
Classifier: Programming Language :: Python :: 3.9
Classifier: Topic :: Utilities
Requires-Python: >=3.6
Requires-Dist: typer
Requires-Dist: pyperclip
Requires-Dist: pyautogui
